libreriawalter/__init__.py
libreriawalter/md.py
libreriawalter/sr.py
libreriawalter-0.0.2.dist-info/METADATA
libreriawalter-0.0.2.dist-info/WHEEL
libreriawalter-0.0.2.dist-info/top_level.txt
libreriawalter-0.0.2.dist-info/RECORD
