Metadata-Version: 2.4
Name: libreriawalter
Version: 0.0.2
Summary: Libreria para calcular suma, resta, multiplicación y división de 2 números, además potencia
Author-email: Walter Becerra <author@example.com>
Classifier: Programming Language :: Python :: 3
Classifier: Operating System :: OS Independent
Requires-Python: >=3.10
